{
    "@view": "{ \n  \"externalUserId\": identifier.ContactID,\n  \"source\": 'yodata-realliving',\n  \"meta\": [\n      {\"name\": \"companyId\", \"value\": additionalProperty.AffiliateID }, \n      {\"name\": \"officeId\", \"value\": additionalProperty.OfficeID },\n      {\"name\": \"contactSystemUserId\", \"value\": identifier.ContactID}, \n      {\"name\": \"role\", \"value\": (type='RealEstateAgent' ? 'AGENT':'BROKER') },\n      {\"name\": \"reflexUri\", \"value\": id}\n  ],\n  \"metaOrgKeys\": [\"companyId\", \"officeId\", \"role\"],\n  \"status\": (additionalProperty.Status = 'Active' ? 'ACTIVE' : 'DISABLED'),\n  \"localLanguage\": availableLanguage[0].name[],\n  \"localCountry\": address[country][0].country,\n  \"email\": (**.email),\n  \"firstName\": givenName,\n  \"lastName\": familyName,\n  \"street1\": $join(address[0].streetAddress,', '),\n  \"city\": address[0].addressLocality,\n  \"state\": address[0].addressRegion,\n  \"country\": address[0].addressCountry,\n  \"postalCode\": address[0].postalCode,\n  \"userImageUrl\": image.url,\n  \"companyId\": additionalProperty.AffiliateID,\n  \"officeId\": additionalProperty.OfficeID,\n  \"officeName\": additionalProperty.OfficeDBA,\n  \"officeUrl\": additionalProperty.OfficeUrl,\n  \"officeEmail\": additionalProperty.OfficeEmail,\n  \"agentProfilePage\": url',\n  \"phone1\": telephone,\n  \"phone1Type\": contactPoint[telephone][0].name,\n  \"phone2\": contactPoint[telephone][1].telephone,\n  \"phone2Type\": contactPoint[telephone][1].name,\n  \"phone3\": contactPoint[telephone][2].telephone,\n  \"phone3Type\": contactPoint[telephone][2].name,\n  \"timeZoneId\": additionalProperty.timeZoneId,\n  \"title\": jobTitle,\n  \"license\": permit.identifier,\n  \"facebookUrl\": url[$contains(\"facebook\")],\n  \"twitterUrl\": url[$contains(\"twitter\")],\n  \"linkedInUrl\": url[$contains(\"linkedin\")]\n  }\n"
}